datamountspawner/__init__.py
datamountspawner/_version.py
datamountspawner/spawner.py
jupyterhub_datamountspawner-1.2.1.dist-info/METADATA
jupyterhub_datamountspawner-1.2.1.dist-info/WHEEL
jupyterhub_datamountspawner-1.2.1.dist-info/licenses/LICENSE
jupyterhub_datamountspawner-1.2.1.dist-info/RECORD
