Metadata-Version: 2.4
Name: jupyterhub-datamountspawner
Version: 1.2.1
Summary: JupyterHub Spawner for JupyterLab DataMount Extension Integration
Author-email: Tim Kreuzer <t.kreuzer@fz-juelich.de>
License: BSD 3-Clause License
License-File: LICENSE
Keywords: data,jupyterhub,spawner,storage
Requires-Python: >=3.9
Requires-Dist: escapism
Requires-Dist: jinja2
Requires-Dist: jupyterhub>=4.0.0
Requires-Dist: traitlets
Requires-Dist: urllib3
